fastapi_key_auth/__init__.py
fastapi_key_auth/utils.py
fastapi_key_auth/dependency/__init__.py
fastapi_key_auth/dependency/authorizer.py
fastapi_key_auth/middleware/__init__.py
fastapi_key_auth/middleware/authorizer.py
fastapi_key_auth-0.15.5.dist-info/METADATA
fastapi_key_auth-0.15.5.dist-info/WHEEL
fastapi_key_auth-0.15.5.dist-info/licenses/LICENSE
fastapi_key_auth-0.15.5.dist-info/RECORD
