Metadata-Version: 2.4
Name: fastapi-key-auth
Version: 0.15.5
Summary: API key validation Middleware
Author-email: Benjamin Ramser <iwpnd@posteo.de>
License-Expression: MIT
License-File: LICENSE
Keywords: api key,fastapi,security
Classifier: Intended Audience :: Developers
Classifier: Programming Language :: Python
Classifier: Programming Language :: Python :: 3
Classifier: Programming Language :: Python :: 3.9
Classifier: Programming Language :: Python :: 3.10
Classifier: Programming Language :: Python :: 3.11
Classifier: Programming Language :: Python :: 3.12
Classifier: Programming Language :: Python :: 3.13
Classifier: Topic :: Software Development :: Libraries :: Python Modules
Requires-Python: <4.0,>=3.9
Requires-Dist: fastapi>=0.100.0
Requires-Dist: starlette>=0.25.0
